Topsis/102103608.py
Topsis/__init__.py
Topsis_Palak_102103608-1.0.0.dist-info/LICENSE.txt
Topsis_Palak_102103608-1.0.0.dist-info/METADATA
Topsis_Palak_102103608-1.0.0.dist-info/WHEEL
Topsis_Palak_102103608-1.0.0.dist-info/entry_points.txt
Topsis_Palak_102103608-1.0.0.dist-info/top_level.txt
Topsis_Palak_102103608-1.0.0.dist-info/RECORD
