Metadata-Version: 2.1
Name: Topsis-Palak-102103608
Version: 1.0.0
Summary: Performs TOPSIS
Home-page: https://github.com/palakga-rg
Author: Palak
Author-email: palak98039@gmail.com
License: MIT
Classifier: License :: OSI Approved :: MIT License
Classifier: Programming Language :: Python :: 3.6
Classifier: Programming Language :: Python :: 3.7
Classifier: Programming Language :: Python :: 3.8
License-File: LICENSE.txt
